{
  "indexes": [
    {
      "collectionGroup": "posts",
      "queryScope": "COLLECTION",
      "fields": [
        { "fieldPath": "status",    "order": "ASCENDING"  },
        { "fieldPath": "createdAt", "order": "DESCENDING" }
      ]
    },
    {
      "collectionGroup": "posts",
      "queryScope": "COLLECTION",
      "fields": [
        { "fieldPath": "status",      "order": "ASCENDING"  },
        { "fieldPath": "scheduledAt", "order": "ASCENDING"  }
      ]
    },
    {
      "collectionGroup": "posts",
      "queryScope": "COLLECTION",
      "fields": [
        { "fieldPath": "status",    "order": "ASCENDING"  },
        { "fieldPath": "updatedAt", "order": "DESCENDING" }
      ]
    },
    {
      "collectionGroup": "posts",
      "queryScope": "COLLECTION",
      "fields": [
        { "fieldPath": "campaignId", "order": "ASCENDING"  },
        { "fieldPath": "createdAt",  "order": "DESCENDING" }
      ]
    },
    {
      "collectionGroup": "agendamentos",
      "queryScope": "COLLECTION",
      "fields": [
        { "fieldPath": "status",      "order": "ASCENDING" },
        { "fieldPath": "scheduledAt", "order": "ASCENDING" }
      ]
    },
    {
      "collectionGroup": "campanhas",
      "queryScope": "COLLECTION",
      "fields": [
        { "fieldPath": "status",    "order": "ASCENDING"  },
        { "fieldPath": "createdAt", "order": "DESCENDING" }
      ]
    },
    {
      "collectionGroup": "trafegoPago",
      "queryScope": "COLLECTION",
      "fields": [
        { "fieldPath": "campaignId", "order": "ASCENDING"  },
        { "fieldPath": "startDate",  "order": "DESCENDING" }
      ]
    },
    {
      "collectionGroup": "approvals",
      "queryScope": "COLLECTION",
      "fields": [
        { "fieldPath": "uid",       "order": "ASCENDING"  },
        { "fieldPath": "status",    "order": "ASCENDING"  },
        { "fieldPath": "createdAt", "order": "DESCENDING" }
      ]
    },
    {
      "collectionGroup": "approvals",
      "queryScope": "COLLECTION",
      "fields": [
        { "fieldPath": "expiresAt", "order": "ASCENDING" },
        { "fieldPath": "status",    "order": "ASCENDING" }
      ]
    },
    {
      "collectionGroup": "connectedAccounts",
      "queryScope": "COLLECTION",
      "fields": [
        { "fieldPath": "platform",    "order": "ASCENDING"  },
        { "fieldPath": "connectedAt", "order": "DESCENDING" }
      ]
    }
  ],
  "fieldOverrides": []
}
